LICENSE
MANIFEST.in
netpbm.py
setup.py
netpbm.egg-info/PKG-INFO
netpbm.egg-info/SOURCES.txt
netpbm.egg-info/dependency_links.txt
netpbm.egg-info/top_level.txt
netpbm.egg-info/zip-safe